{"ticker": "AGD.AX", "name": "Austral Gold Limited", "sector": "Basic Materials", "industry": "Other Precious Metals & Mining", "exchange": "ASX", "currency": "AUD", "market_cap": 136961248, "market_cap_b": 0.14, "pe_trailing": null, "pe_forward": null, "pb_ratio": 6.932026, "ps_ratio": 3.774805, "ev_ebitda": -65.194, "peg_ratio": null, "graham_number_check": null, "roe": -57.03, "roa": -5.97, "gross_margin": 17.89, "operating_margin": -3.87, "profit_margin": -28.64, "revenue_growth": -2.7, "earnings_growth": null, "current_ratio": 0.645, "debt_to_equity": 2.19, "quick_ratio": 0.328, "total_debt": 28532000, "total_cash": 5932000, "net_cash": -22600000, "free_cash_flow": -10026750, "operating_cash_flow": -4795000, "fcf_yield": -7.32, "dividend_yield": null, "payout_ratio": 0.0, "shares_outstanding": 668103679, "eps_positive_years": 0, "eps_total_years": 4, "earnings_cagr": null, "margin_trend": "declining", "margin_trend_delta": -19.6, "roic": -36.93, "capex_to_net_income": null, "shares_change_pct": 0.0, "shares_trend": "stable", "dividend_years": 9, "insider_pct": 83.4, "institution_pct": 0.07, "valid": true, "fetch_time": "2026-03-03T14:07:28.172110"}