{"ticker": "AUC.AX", "name": "Ausgold Limited", "sector": "Basic Materials", "industry": "Gold", "exchange": "ASX", "currency": "AUD", "market_cap": 638256512, "market_cap_b": 0.64, "pe_trailing": null, "pe_forward": -41.60714, "pb_ratio": 3.1657608, "ps_ratio": null, "ev_ebitda": -57.821, "peg_ratio": null, "graham_number_check": null, "roe": -8.54, "roa": -5.02, "gross_margin": 0.0, "operating_margin": 0.0, "profit_margin": 0.0, "revenue_growth": null, "earnings_growth": null, "current_ratio": 3.662, "debt_to_equity": 0.1, "quick_ratio": 3.653, "total_debt": 19579264, "total_cash": 75602864, "net_cash": 56023600, "free_cash_flow": -35625360, "operating_cash_flow": -2754843, "fcf_yield": -5.58, "dividend_yield": null, "payout_ratio": 0.0, "shares_outstanding": 547859741, "eps_positive_years": 0, "eps_total_years": 4, "earnings_cagr": null, "roic": -10.56, "capex_to_net_income": null, "shares_change_pct": 76.13, "shares_trend": "increasing", "dividend_years": 7, "insider_pct": 15.5, "institution_pct": 46.37, "valid": true, "fetch_time": "2026-03-03T14:06:52.681467"}