{"ticker": "BCM.AX", "name": "Brazilian Critical Minerals Limited", "sector": "Basic Materials", "industry": "Gold", "exchange": "ASX", "currency": "AUD", "market_cap": 74167104, "market_cap_b": 0.07, "pe_trailing": null, "pe_forward": null, "pb_ratio": null, "ps_ratio": 1085.6636, "ev_ebitda": -12.721, "peg_ratio": null, "graham_number_check": null, "roe": -518.34, "roa": -131.65, "gross_margin": 100.0, "operating_margin": -3565.33, "profit_margin": 0.0, "revenue_growth": 188.4, "earnings_growth": null, "current_ratio": 1.091, "debt_to_equity": 2.09, "quick_ratio": 1.081, "total_debt": 1127535, "total_cash": 1698485, "net_cash": 570950, "free_cash_flow": -2732075, "operating_cash_flow": -4106449, "fcf_yield": -3.68, "dividend_yield": null, "payout_ratio": 0.0, "shares_outstanding": 1951765832, "eps_positive_years": 0, "eps_total_years": 4, "earnings_cagr": null, "roic": -1575.57, "capex_to_net_income": null, "shares_change_pct": 89.93, "shares_trend": "increasing", "dividend_years": 18, "insider_pct": 29.2, "institution_pct": 8.31, "valid": true, "fetch_time": "2026-03-03T14:48:30.330694"}