{"ticker": "BOC.AX", "name": "Bougainville Copper Limited", "sector": "Basic Materials", "industry": "Other Precious Metals & Mining", "exchange": "ASX", "currency": "AUD", "market_cap": 314834080, "market_cap_b": 0.31, "pe_trailing": null, "pe_forward": null, "pb_ratio": 3.9646466, "ps_ratio": null, "ev_ebitda": null, "peg_ratio": null, "graham_number_check": null, "roe": -17.46, "roa": -9.4, "gross_margin": 20.64, "operating_margin": 0.0, "profit_margin": 0.0, "revenue_growth": -10.4, "earnings_growth": null, "current_ratio": 2.932, "debt_to_equity": 0.0, "quick_ratio": 2.932, "total_debt": 0, "total_cash": 0, "net_cash": 0, "free_cash_flow": -8995125, "operating_cash_flow": null, "fcf_yield": -2.86, "dividend_yield": null, "payout_ratio": 0.0, "shares_outstanding": 401062500, "eps_positive_years": 0, "eps_total_years": 4, "earnings_cagr": null, "roic": -15.68, "capex_to_net_income": null, "shares_change_pct": 0.0, "shares_trend": "stable", "dividend_years": 24, "insider_pct": 74.76, "institution_pct": 0.01, "valid": true, "fetch_time": "2026-03-03T14:47:47.712662"}