{"ticker": "BRE.AX", "name": "BRZLINRARE FPO [BRE]", "sector": "Basic Materials", "industry": "Other Precious Metals & Mining", "exchange": "ASX", "currency": "AUD", "market_cap": 1503174656, "market_cap_b": 1.5, "pe_trailing": null, "pe_forward": -33.0303, "pb_ratio": 19.464285, "ps_ratio": null, "ev_ebitda": -32.826, "peg_ratio": null, "graham_number_check": null, "roe": -40.71, "roa": -27.88, "gross_margin": 0.0, "operating_margin": 0.0, "profit_margin": 0.0, "revenue_growth": null, "earnings_growth": null, "current_ratio": 22.909, "debt_to_equity": null, "quick_ratio": 22.453, "total_debt": 0, "total_cash": 67368848, "net_cash": 67368848, "free_cash_flow": -20957536, "operating_cash_flow": -28539012, "fcf_yield": -1.39, "dividend_yield": null, "payout_ratio": 0.0, "shares_outstanding": 275811885, "eps_positive_years": 0, "eps_total_years": 3, "earnings_cagr": null, "roic": -336.99, "capex_to_net_income": null, "shares_change_pct": 31588.45, "shares_trend": "increasing", "dividend_years": 0, "insider_pct": 56.12, "institution_pct": 13.86, "valid": true, "fetch_time": "2026-03-03T14:48:33.751840"}