{"ticker": "BXMT", "name": "Blackstone Mortgage Trust, Inc.", "sector": "Real Estate", "industry": "REIT - Mortgage", "exchange": "US", "currency": "USD", "market_cap": 3306289408, "market_cap_b": 3.31, "pe_trailing": 31.190475, "pe_forward": 9.689348, "pb_ratio": 0.9571825, "ps_ratio": 7.5151825, "ev_ebitda": null, "peg_ratio": null, "graham_number_check": 29.854976836687502, "roe": 3.01, "roa": 0.55, "gross_margin": 100.0, "operating_margin": 23.33, "profit_margin": 24.91, "revenue_growth": 49.4, "earnings_growth": 9.7, "current_ratio": 94.519, "debt_to_equity": 4.62, "quick_ratio": 94.384, "total_debt": 16178449408, "total_cash": 463017984, "net_cash": -15715431424, "free_cash_flow": null, "operating_cash_flow": 275872992, "fcf_yield": null, "dividend_yield": 957.0, "payout_ratio": 298.41, "shares_outstanding": 168259000, "eps_positive_years": 3, "eps_total_years": 4, "earnings_cagr": null, "roic": null, "capex_to_net_income": null, "shares_change_pct": 2.74, "shares_trend": "increasing", "dividend_years": 39, "insider_pct": 1.25, "institution_pct": 65.19, "valid": true, "fetch_time": "2026-03-03T08:23:57.326721"}