{"ticker": "CBSH", "name": "Commerce Bancshares, Inc.", "sector": "Financial Services", "industry": "Banks - Regional", "exchange": "US", "currency": "USD", "market_cap": 7624258560, "market_cap_b": 7.62, "pe_trailing": 12.8069315, "pe_forward": 11.769122, "pb_ratio": 1.8793361, "ps_ratio": 4.4543037, "ev_ebitda": null, "peg_ratio": null, "graham_number_check": 24.068528698177147, "roe": 15.97, "roa": 1.76, "gross_margin": 0.0, "operating_margin": 42.57, "profit_margin": 33.08, "revenue_growth": 6.5, "earnings_growth": 5.0, "current_ratio": null, "debt_to_equity": null, "quick_ratio": null, "total_debt": 3052690944, "total_cash": 4489133056, "net_cash": 1436442112, "free_cash_flow": null, "operating_cash_flow": 645136000, "fcf_yield": null, "dividend_yield": 213.0, "payout_ratio": 26.26, "shares_outstanding": 147357138, "eps_positive_years": 4, "eps_total_years": 4, "earnings_cagr": -0.21, "roic": null, "capex_to_net_income": 8.77, "shares_change_pct": -4.39, "shares_trend": "declining", "dividend_years": 40, "insider_pct": 2.53, "institution_pct": 69.01, "valid": true, "fetch_time": "2026-03-03T08:09:13.750210"}