{"ticker": "CFLT", "name": "Confluent, Inc.", "sector": "Technology", "industry": "Software - Infrastructure", "exchange": "US", "currency": "USD", "market_cap": 10979686400, "market_cap_b": 10.98, "pe_trailing": null, "pe_forward": 46.26839, "pb_ratio": 9.351203, "ps_ratio": 9.410503, "ev_ebitda": -29.674, "peg_ratio": null, "graham_number_check": null, "roe": -27.72, "roa": -8.09, "gross_margin": 74.29, "operating_margin": -27.53, "profit_margin": -25.31, "revenue_growth": 20.5, "earnings_growth": null, "current_ratio": 3.83, "debt_to_equity": 0.95, "quick_ratio": 3.592, "total_debt": 1105371008, "total_cash": 2053971968, "net_cash": 948600960, "free_cash_flow": 210338752, "operating_cash_flow": 64274000, "fcf_yield": 1.92, "dividend_yield": null, "payout_ratio": 0.0, "shares_outstanding": 308661566, "eps_positive_years": 0, "eps_total_years": 4, "earnings_cagr": null, "margin_trend": "expanding", "margin_trend_delta": 8.84, "roic": -14.79, "capex_to_net_income": null, "shares_change_pct": 23.07, "shares_trend": "increasing", "dividend_years": 0, "insider_pct": 1.2, "institution_pct": 90.55, "valid": true, "fetch_time": "2026-03-03T08:04:04.594341"}