{"ticker": "CG1.AX", "name": "Carbonxt Group Limited", "sector": "Basic Materials", "industry": "Specialty Chemicals", "exchange": "ASX", "currency": "AUD", "market_cap": 34666428, "market_cap_b": 0.03, "pe_trailing": null, "pe_forward": null, "pb_ratio": 3.6363635, "ps_ratio": 2.1405187, "ev_ebitda": -37.298, "peg_ratio": null, "graham_number_check": null, "roe": -67.76, "roa": -4.3, "gross_margin": 52.37, "operating_margin": -4.15, "profit_margin": -41.75, "revenue_growth": 32.0, "earnings_growth": null, "current_ratio": 0.232, "debt_to_equity": 1.61, "quick_ratio": 0.171, "total_debt": 14833598, "total_cash": 480687, "net_cash": -14352911, "free_cash_flow": -4064178, "operating_cash_flow": -4752205, "fcf_yield": -11.72, "dividend_yield": null, "payout_ratio": 0.0, "shares_outstanding": 433330377, "eps_positive_years": 0, "eps_total_years": 4, "earnings_cagr": null, "margin_trend": "expanding", "margin_trend_delta": 11.19, "roic": -21.61, "capex_to_net_income": null, "shares_change_pct": 97.49, "shares_trend": "increasing", "dividend_years": 0, "insider_pct": 36.28, "institution_pct": 4.7, "valid": true, "fetch_time": "2026-03-03T14:51:25.578637"}