{"ticker": "CIG", "name": "Companhia Energ\u00e9tica de Minas Gerais - CEMIG", "sector": "Utilities", "industry": "Utilities - Diversified", "exchange": "US", "currency": "USD", "market_cap": 7217001984, "market_cap_b": 7.22, "pe_trailing": 5.181818, "pe_forward": 15.199999, "pb_ratio": 1.1652225, "ps_ratio": 0.17010342, "ev_ebitda": 2.822, "peg_ratio": null, "graham_number_check": 6.037970924505, "roe": 14.16, "roa": 5.61, "gross_margin": 13.59, "operating_margin": 10.19, "profit_margin": 9.47, "revenue_growth": 4.6, "earnings_growth": -75.7, "current_ratio": 0.896, "debt_to_equity": 0.55, "quick_ratio": 0.712, "total_debt": 15835669504, "total_cash": 2317042944, "net_cash": -13518626560, "free_cash_flow": -2693186048, "operating_cash_flow": 4283584000, "fcf_yield": -37.32, "dividend_yield": 646.0, "payout_ratio": 64.43, "shares_outstanding": 1904080104, "eps_positive_years": 4, "eps_total_years": 4, "earnings_cagr": 17.36, "margin_trend": "stable", "margin_trend_delta": -0.32, "roic": 14.71, "capex_to_net_income": 12.91, "shares_change_pct": -0.04, "shares_trend": "stable", "dividend_years": 24, "insider_pct": 0.0, "institution_pct": 7.64, "valid": true, "fetch_time": "2026-03-03T08:11:27.531692"}