{"ticker": "COD.AX", "name": "Coda Minerals Limited", "sector": "Basic Materials", "industry": "Other Industrial Metals & Mining", "exchange": "ASX", "currency": "AUD", "market_cap": 74404136, "market_cap_b": 0.07, "pe_trailing": null, "pe_forward": -3.508772, "pb_ratio": 2.5974026, "ps_ratio": 148808.27, "ev_ebitda": -7.631, "peg_ratio": null, "graham_number_check": null, "roe": -28.01, "roa": -16.95, "gross_margin": 100.0, "operating_margin": -1010756.3, "profit_margin": 0.0, "revenue_growth": null, "earnings_growth": null, "current_ratio": 7.565, "debt_to_equity": 0.01, "quick_ratio": 7.396, "total_debt": 163368, "total_cash": 11249399, "net_cash": 11086031, "free_cash_flow": -3107355, "operating_cash_flow": -5878632, "fcf_yield": -4.18, "dividend_yield": null, "payout_ratio": 0.0, "shares_outstanding": 372020666, "eps_positive_years": 0, "eps_total_years": 4, "earnings_cagr": null, "roic": -20.42, "capex_to_net_income": null, "shares_change_pct": 78.81, "shares_trend": "increasing", "dividend_years": 0, "insider_pct": 29.99, "institution_pct": 0.0, "valid": true, "fetch_time": "2026-03-03T14:55:57.196650"}