{"ticker": "CRNX", "name": "Crinetics Pharmaceuticals, Inc.", "sector": "Healthcare", "industry": "Biotechnology", "exchange": "US", "currency": "USD", "market_cap": 4170181632, "market_cap_b": 4.17, "pe_trailing": null, "pe_forward": -10.060243, "pb_ratio": 3.919075, "ps_ratio": 541.8635, "ev_ebitda": -6.395, "peg_ratio": null, "graham_number_check": null, "roe": -40.17, "roa": -25.22, "gross_margin": 0.0, "operating_margin": -2169.55, "profit_margin": 0.0, "revenue_growth": null, "earnings_growth": null, "current_ratio": 12.323, "debt_to_equity": 0.05, "quick_ratio": 12.09, "total_debt": 48541000, "total_cash": 1027889024, "net_cash": 979348024, "free_cash_flow": -206911632, "operating_cash_flow": -377921984, "fcf_yield": -4.96, "dividend_yield": null, "payout_ratio": 0.0, "shares_outstanding": 102511840, "eps_positive_years": 0, "eps_total_years": 4, "earnings_cagr": null, "roic": -22.85, "capex_to_net_income": null, "shares_change_pct": 95.23, "shares_trend": "increasing", "dividend_years": 0, "insider_pct": 2.25, "institution_pct": 121.64, "valid": true, "fetch_time": "2026-03-03T08:19:19.980082"}