{"ticker": "CSW", "name": "CSW Industrials, Inc.", "sector": "Industrials", "industry": "Specialty Industrial Machinery", "exchange": "US", "currency": "USD", "market_cap": 4927584768, "market_cap_b": 4.93, "pe_trailing": 39.060844, "pe_forward": 24.950739, "pb_ratio": 4.5577316, "ps_ratio": 4.9072785, "ev_ebitda": 24.197, "peg_ratio": null, "graham_number_check": 178.02884302147044, "roe": 11.87, "roa": 6.1, "gross_margin": 42.72, "operating_margin": 7.44, "profit_margin": 12.64, "revenue_growth": 20.3, "earnings_growth": -61.3, "current_ratio": 2.364, "debt_to_equity": 0.81, "quick_ratio": 0.817, "total_debt": 876419008, "total_cash": 40238000, "net_cash": -836181008, "free_cash_flow": 80793872, "operating_cash_flow": 178628000, "fcf_yield": 1.64, "dividend_yield": 37.0, "payout_ratio": 13.91, "shares_outstanding": 16470230, "eps_positive_years": 4, "eps_total_years": 4, "earnings_cagr": 19.78, "margin_trend": "expanding", "margin_trend_delta": 3.92, "roic": 14.84, "capex_to_net_income": 11.9, "shares_change_pct": 9.38, "shares_trend": "increasing", "dividend_years": 6, "insider_pct": 4.2, "institution_pct": 104.94, "valid": true, "fetch_time": "2026-03-03T08:16:58.060284"}