{"ticker": "EEFT", "name": "Euronet Worldwide, Inc.", "sector": "Technology", "industry": "Software - Infrastructure", "exchange": "US", "currency": "USD", "market_cap": 3013762560, "market_cap_b": 3.01, "pe_trailing": 10.479532, "pe_forward": 5.8826423, "pb_ratio": 2.1561787, "ps_ratio": 0.7100897, "ev_ebitda": 4.968, "peg_ratio": null, "graham_number_check": 22.5957436843684, "roe": 24.53, "roa": 5.38, "gross_margin": 24.52, "operating_margin": 8.72, "profit_margin": 7.29, "revenue_growth": 5.9, "earnings_growth": 9.1, "current_ratio": 1.108, "debt_to_equity": 1.65, "quick_ratio": 0.525, "total_debt": 2177299968, "total_cash": 1690599936, "net_cash": -486700032, "free_cash_flow": 337237504, "operating_cash_flow": 559800000, "fcf_yield": 11.19, "dividend_yield": null, "payout_ratio": 0.0, "shares_outstanding": 42044681, "eps_positive_years": 4, "eps_total_years": 4, "earnings_cagr": 44.24, "margin_trend": "expanding", "margin_trend_delta": 3.55, "roic": 27.15, "capex_to_net_income": 38.3, "shares_change_pct": 1.58, "shares_trend": "stable", "dividend_years": 0, "insider_pct": 6.51, "institution_pct": 100.96, "valid": true, "fetch_time": "2026-03-03T08:27:00.221551"}