{"ticker": "EMB.AX", "name": "Embelton Limited", "sector": "Industrials", "industry": "Building Products & Equipment", "exchange": "ASX", "currency": "AUD", "market_cap": 17435492, "market_cap_b": 0.02, "pe_trailing": 17.565216, "pe_forward": null, "pb_ratio": 0.8484721, "ps_ratio": 0.2594744, "ev_ebitda": 10.379, "peg_ratio": null, "graham_number_check": 14.903595706473599, "roe": 4.84, "roa": 3.18, "gross_margin": 22.88, "operating_margin": 2.11, "profit_margin": 1.47, "revenue_growth": 27.2, "earnings_growth": 11.4, "current_ratio": 2.888, "debt_to_equity": 0.32, "quick_ratio": 1.325, "total_debt": 6583000, "total_cash": 76000, "net_cash": -6507000, "free_cash_flow": -3271545, "operating_cash_flow": 57723, "fcf_yield": -18.76, "dividend_yield": 433.0, "payout_ratio": 76.25, "shares_outstanding": 2157857, "eps_positive_years": 4, "eps_total_years": 4, "earnings_cagr": -3.25, "margin_trend": "stable", "margin_trend_delta": -0.75, "roic": 4.36, "capex_to_net_income": 67.57, "shares_change_pct": 0.0, "shares_trend": "stable", "dividend_years": 37, "insider_pct": 90.49, "institution_pct": 0.0, "valid": true, "fetch_time": "2026-03-03T15:05:19.719200"}