{"ticker": "EQU.AX", "name": "Equus Energy Ltd", "sector": "Utilities", "industry": "Utilities - Regulated Gas", "exchange": "ASX", "currency": "AUD", "market_cap": 85950360, "market_cap_b": 0.09, "pe_trailing": null, "pe_forward": null, "pb_ratio": 14.999999, "ps_ratio": 559.6018, "ev_ebitda": null, "peg_ratio": null, "graham_number_check": null, "roe": -16.13, "roa": -12.03, "gross_margin": 100.0, "operating_margin": -321.72, "profit_margin": 0.0, "revenue_growth": -76.4, "earnings_growth": null, "current_ratio": 24.002, "debt_to_equity": null, "quick_ratio": 23.979, "total_debt": 0, "total_cash": 3805190, "net_cash": 3805190, "free_cash_flow": -435036, "operating_cash_flow": -586101, "fcf_yield": -0.51, "dividend_yield": null, "payout_ratio": 0.0, "shares_outstanding": 204643730, "eps_positive_years": 0, "eps_total_years": 4, "earnings_cagr": null, "roic": null, "capex_to_net_income": null, "shares_change_pct": 54.74, "shares_trend": "increasing", "dividend_years": 0, "insider_pct": 46.09, "institution_pct": 9.03, "valid": true, "fetch_time": "2026-03-03T15:07:47.680839"}