{"ticker": "FLOC", "name": "Flowco Holdings Inc.", "sector": "Energy", "industry": "Oil & Gas Equipment & Services", "exchange": "US", "currency": "USD", "market_cap": 2225718528, "market_cap_b": 2.23, "pe_trailing": 12.804347, "pe_forward": 15.434303, "pb_ratio": 2.9978368, "ps_ratio": 2.9296603, "ev_ebitda": 6.9, "peg_ratio": null, "graham_number_check": 38.3853426365696, "roe": 11.98, "roa": 5.79, "gross_margin": 54.38, "operating_margin": 21.53, "profit_margin": 5.45, "revenue_growth": 6.0, "earnings_growth": -81.5, "current_ratio": 3.335, "debt_to_equity": 0.15, "quick_ratio": 1.346, "total_debt": 209363008, "total_cash": 4522000, "net_cash": -204841008, "free_cash_flow": 58932376, "operating_cash_flow": 294369984, "fcf_yield": 2.65, "dividend_yield": 136.0, "payout_ratio": 8.72, "shares_outstanding": 29647189, "eps_positive_years": 3, "eps_total_years": 3, "earnings_cagr": 34.85, "margin_trend": "declining", "margin_trend_delta": -4.68, "roic": null, "capex_to_net_income": 113.01, "shares_change_pct": 0.0, "shares_trend": "stable", "dividend_years": 1, "insider_pct": 20.04, "institution_pct": 77.09, "valid": true, "fetch_time": "2026-03-03T08:31:47.550267"}