{"ticker": "FR", "name": "First Industrial Realty Trust, Inc.", "sector": "Real Estate", "industry": "REIT - Industrial", "exchange": "US", "currency": "USD", "market_cap": 8674530304, "market_cap_b": 8.67, "pe_trailing": 33.95722, "pe_forward": 33.533833, "pb_ratio": 3.1488643, "ps_ratio": 11.922753, "ev_ebitda": 21.854, "peg_ratio": null, "graham_number_check": 106.926677785246, "roe": 9.59, "roa": 3.52, "gross_margin": 73.59, "operating_margin": 42.12, "profit_margin": 34.01, "revenue_growth": 7.7, "earnings_growth": 15.2, "current_ratio": 0.515, "debt_to_equity": 0.93, "quick_ratio": 0.504, "total_debt": 2573937920, "total_cash": 78032000, "net_cash": -2495905920, "free_cash_flow": 421644992, "operating_cash_flow": 461263008, "fcf_yield": 4.86, "dividend_yield": 315.0, "payout_ratio": 95.19, "shares_outstanding": 132524261, "eps_positive_years": 4, "eps_total_years": 4, "earnings_cagr": -8.89, "margin_trend": "stable", "margin_trend_delta": 0.27, "roic": 4.47, "capex_to_net_income": null, "shares_change_pct": 0.25, "shares_trend": "stable", "dividend_years": 31, "insider_pct": 0.47, "institution_pct": 102.36, "valid": true, "fetch_time": "2026-03-03T08:07:53.313405"}