{"ticker": "HG", "name": "Hamilton Insurance Group, Ltd.", "sector": "Financial Services", "industry": "Insurance - Reinsurance", "exchange": "US", "currency": "USD", "market_cap": 3124378624, "market_cap_b": 3.12, "pe_trailing": 5.6846843, "pe_forward": 6.4479733, "pb_ratio": 1.1070952, "ps_ratio": 1.0731132, "ev_ebitda": 2.328, "peg_ratio": null, "graham_number_check": 6.29348670204536, "roe": 32.62, "roa": 6.12, "gross_margin": 39.35, "operating_margin": 26.88, "profit_margin": 19.81, "revenue_growth": 29.4, "earnings_growth": 433.3, "current_ratio": 2.011, "debt_to_equity": 0.06, "quick_ratio": 1.145, "total_debt": 156884000, "total_cash": 1262818048, "net_cash": 1105934048, "free_cash_flow": 840949248, "operating_cash_flow": 842350016, "fcf_yield": 26.92, "dividend_yield": null, "payout_ratio": 0.0, "shares_outstanding": 66305707, "eps_positive_years": 3, "eps_total_years": 4, "earnings_cagr": 20.78, "roic": 32.6, "capex_to_net_income": null, "shares_change_pct": -7.74, "shares_trend": "declining", "dividend_years": 0, "insider_pct": 8.95, "institution_pct": 86.12, "valid": true, "fetch_time": "2026-03-03T08:31:54.855030"}