{"ticker": "HWM", "name": "Howmet Aerospace Inc.", "sector": "Industrials", "industry": "Aerospace & Defense", "exchange": "US", "currency": "USD", "market_cap": 106706771968, "market_cap_b": 106.71, "pe_trailing": 71.45821, "pe_forward": 48.54543, "pb_ratio": 19.889713, "ps_ratio": 12.931019, "ev_ebitda": 45.546, "peg_ratio": null, "graham_number_check": 1421.28328839373, "roe": 30.44, "roa": 12.13, "gross_margin": 34.17, "operating_margin": 26.34, "profit_margin": 18.27, "revenue_growth": 14.6, "earnings_growth": 20.3, "current_ratio": 2.134, "debt_to_equity": 0.6, "quick_ratio": 0.868, "total_debt": 3212999936, "total_cash": 742000000, "net_cash": -2470999936, "free_cash_flow": 917249984, "operating_cash_flow": 1884000000, "fcf_yield": 0.86, "dividend_yield": 17.0, "payout_ratio": 11.86, "shares_outstanding": 400940063, "eps_positive_years": 4, "eps_total_years": 4, "earnings_cagr": 33.91, "margin_trend": "expanding", "margin_trend_delta": 6.63, "roic": 20.27, "capex_to_net_income": 30.04, "shares_change_pct": -2.56, "shares_trend": "declining", "dividend_years": 9, "insider_pct": 1.3, "institution_pct": 94.28, "valid": true, "fetch_time": "2026-03-03T07:44:02.265122"}