{"ticker": "INSM", "name": "Insmed Incorporated", "sector": "Healthcare", "industry": "Biotechnology", "exchange": "US", "currency": "USD", "market_cap": 31539556352, "market_cap_b": 31.54, "pe_trailing": null, "pe_forward": 394.6595, "pb_ratio": 42.423893, "ps_ratio": 52.00917, "ev_ebitda": -31.474, "peg_ratio": null, "graham_number_check": null, "roe": -249.28, "roa": -28.99, "gross_margin": 79.73, "operating_margin": -94.64, "profit_margin": -210.54, "revenue_growth": 152.6, "earnings_growth": null, "current_ratio": 3.827, "debt_to_equity": 1.01, "quick_ratio": 3.35, "total_debt": 749536000, "total_cash": 1430046976, "net_cash": 680510976, "free_cash_flow": -534054880, "operating_cash_flow": -935014016, "fcf_yield": -1.69, "dividend_yield": null, "payout_ratio": 0.0, "shares_outstanding": 215551896, "eps_positive_years": 0, "eps_total_years": 4, "earnings_cagr": null, "margin_trend": "expanding", "margin_trend_delta": 2.19, "roic": -91.52, "capex_to_net_income": null, "shares_change_pct": 57.94, "shares_trend": "increasing", "dividend_years": 0, "insider_pct": 0.71, "institution_pct": 102.35, "valid": true, "fetch_time": "2026-03-03T07:52:21.152431"}