{"ticker": "LPE.AX", "name": "Locality Planning Energy Holdings Limited", "sector": "Utilities", "industry": "Utilities - Regulated Electric", "exchange": "ASX", "currency": "AUD", "market_cap": 18262444, "market_cap_b": 0.02, "pe_trailing": null, "pe_forward": null, "pb_ratio": 2.4390244, "ps_ratio": 0.43862343, "ev_ebitda": 9.919, "peg_ratio": null, "graham_number_check": null, "roe": -38.32, "roa": 2.55, "gross_margin": 24.83, "operating_margin": 1.07, "profit_margin": -8.39, "revenue_growth": -4.4, "earnings_growth": null, "current_ratio": 1.243, "debt_to_equity": 0.32, "quick_ratio": 1.162, "total_debt": 2375899, "total_cash": 9400288, "net_cash": 7024389, "free_cash_flow": 5392375, "operating_cash_flow": 7931483, "fcf_yield": 29.53, "dividend_yield": null, "payout_ratio": 0.0, "shares_outstanding": 182624436, "eps_positive_years": 3, "eps_total_years": 4, "earnings_cagr": 21.58, "margin_trend": "expanding", "margin_trend_delta": 10.26, "roic": 10.56, "capex_to_net_income": 5.57, "shares_change_pct": 186.56, "shares_trend": "increasing", "dividend_years": 0, "insider_pct": 51.2, "institution_pct": 20.76, "valid": true, "fetch_time": "2026-03-03T15:32:29.503885"}