{"ticker": "MKTX", "name": "MarketAxess Holdings Inc.", "sector": "Financial Services", "industry": "Capital Markets", "exchange": "US", "currency": "USD", "market_cap": 7138788352, "market_cap_b": 7.14, "pe_trailing": 28.923193, "pe_forward": 21.18436, "pb_ratio": 5.9972525, "ps_ratio": 8.435612, "ev_ebitda": 15.355, "peg_ratio": null, "graham_number_check": 173.4596915272325, "roe": 19.39, "roa": 11.64, "gross_margin": 62.02, "operating_margin": 36.82, "profit_margin": 29.14, "revenue_growth": 3.5, "earnings_growth": 45.3, "current_ratio": 3.35, "debt_to_equity": 0.25, "quick_ratio": 2.805, "total_debt": 284937984, "total_cash": 620505984, "net_cash": 335568000, "free_cash_flow": 224411120, "operating_cash_flow": 382139008, "fcf_yield": 3.14, "dividend_yield": 162.0, "payout_ratio": 45.78, "shares_outstanding": 35548265, "eps_positive_years": 4, "eps_total_years": 4, "earnings_cagr": -0.36, "margin_trend": "declining", "margin_trend_delta": -5.4, "roic": 28.15, "capex_to_net_income": 23.52, "shares_change_pct": 0.5, "shares_trend": "stable", "dividend_years": 16, "insider_pct": 3.07, "institution_pct": 110.88, "valid": true, "fetch_time": "2026-03-03T08:10:59.294850"}