{"ticker": "NOW", "name": "ServiceNow, Inc.", "sector": "Technology", "industry": "Software - Application", "exchange": "US", "currency": "USD", "market_cap": 115453739008, "market_cap_b": 115.45, "pe_trailing": 65.52096, "pe_forward": 21.839928, "pb_ratio": 8.839163, "ps_ratio": 8.695115, "ev_ebitda": 40.384, "peg_ratio": null, "graham_number_check": 579.15044535648, "roe": 15.49, "roa": 5.39, "gross_margin": 77.53, "operating_margin": 16.51, "profit_margin": 13.16, "revenue_growth": 20.7, "earnings_growth": 3.4, "current_ratio": 1.003, "debt_to_equity": 0.19, "quick_ratio": 0.86, "total_debt": 2403000064, "total_cash": 6284000256, "net_cash": 3881000192, "free_cash_flow": 4951625216, "operating_cash_flow": 5443999744, "fcf_yield": 4.29, "dividend_yield": null, "payout_ratio": 0.0, "shares_outstanding": 1046000000, "eps_positive_years": 4, "eps_total_years": 4, "earnings_cagr": 52.29, "margin_trend": "stable", "margin_trend_delta": -0.75, "roic": 11.75, "capex_to_net_income": 52.12, "shares_change_pct": 5.06, "shares_trend": "increasing", "dividend_years": 0, "insider_pct": 0.38, "institution_pct": 89.62, "valid": true, "fetch_time": "2026-03-03T07:43:46.702015"}