{"ticker": "PLAB", "name": "Photronics, Inc.", "sector": "Technology", "industry": "Semiconductor Equipment & Materials", "exchange": "US", "currency": "USD", "market_cap": 2181257216, "market_cap_b": 2.18, "pe_trailing": 15.782052, "pe_forward": 16.635136, "pb_ratio": 1.7619276, "ps_ratio": 2.5298092, "ev_ebitda": 6.735, "peg_ratio": null, "graham_number_check": 27.806833003435198, "roe": 12.22, "roa": 7.31, "gross_margin": 35.14, "operating_margin": 24.38, "profit_margin": 15.83, "revenue_growth": 6.1, "earnings_growth": 8.8, "current_ratio": 4.579, "debt_to_equity": 0.0, "quick_ratio": 4.047, "total_debt": 21000, "total_cash": 636870976, "net_cash": 636849976, "free_cash_flow": 36478500, "operating_cash_flow": 266586000, "fcf_yield": 1.67, "dividend_yield": null, "payout_ratio": 0.0, "shares_outstanding": 57922773, "eps_positive_years": 4, "eps_total_years": 4, "earnings_cagr": 3.52, "margin_trend": "stable", "margin_trend_delta": -0.38, "roic": 22.72, "capex_to_net_income": 137.99, "shares_change_pct": -5.19, "shares_trend": "declining", "dividend_years": 0, "insider_pct": 3.81, "institution_pct": 98.89, "valid": true, "fetch_time": "2026-03-03T08:31:31.968210"}