{"ticker": "PLTR", "name": "Palantir Technologies Inc.", "sector": "Technology", "industry": "Software - Infrastructure", "exchange": "US", "currency": "USD", "market_cap": 347199537152, "market_cap_b": 347.2, "pe_trailing": 234.14516, "pe_forward": 78.54967, "pb_ratio": 46.995792, "ps_ratio": 77.57876, "ev_ebitda": 236.33, "peg_ratio": null, "graham_number_check": 11003.837237166721, "roe": 25.98, "roa": 11.6, "gross_margin": 82.37, "operating_margin": 40.9, "profit_margin": 36.31, "revenue_growth": 70.0, "earnings_growth": 647.6, "current_ratio": 7.11, "debt_to_equity": 0.03, "quick_ratio": 6.992, "total_debt": 229338000, "total_cash": 7177042944, "net_cash": 6947704944, "free_cash_flow": 1260918400, "operating_cash_flow": 2134472960, "fcf_yield": 0.36, "dividend_yield": null, "payout_ratio": 0.0, "shares_outstanding": 2291470751, "eps_positive_years": 3, "eps_total_years": 4, "earnings_cagr": null, "margin_trend": "expanding", "margin_trend_delta": 3.8, "roic": 17.12, "capex_to_net_income": 2.09, "shares_change_pct": 13.92, "shares_trend": "increasing", "dividend_years": 0, "insider_pct": 3.76, "institution_pct": 61.73, "valid": true, "fetch_time": "2026-03-03T07:40:43.533860"}