{"ticker": "RYD.AX", "name": "Ryder Capital Limited", "sector": "Financial Services", "industry": "Asset Management", "exchange": "ASX", "currency": "AUD", "market_cap": 161905088, "market_cap_b": 0.16, "pe_trailing": null, "pe_forward": null, "pb_ratio": null, "ps_ratio": null, "ev_ebitda": null, "peg_ratio": null, "graham_number_check": null, "roe": null, "roa": null, "gross_margin": 0.0, "operating_margin": 0.0, "profit_margin": 0.0, "revenue_growth": null, "earnings_growth": null, "current_ratio": null, "debt_to_equity": null, "quick_ratio": null, "total_debt": 0, "total_cash": 0, "net_cash": 0, "free_cash_flow": null, "operating_cash_flow": null, "fcf_yield": null, "dividend_yield": 647.0, "payout_ratio": 349.26, "shares_outstanding": 80549795, "eps_positive_years": 4, "eps_total_years": 4, "earnings_cagr": -10.62, "roic": null, "capex_to_net_income": null, "shares_change_pct": -4.76, "shares_trend": "declining", "dividend_years": 7, "insider_pct": 50.33, "institution_pct": 6.06, "valid": true, "fetch_time": "2026-03-03T16:02:28.022330"}