{"ticker": "SFG.AX", "name": "Seafarms Group Limited", "sector": "Consumer Defensive", "industry": "Farm Products", "exchange": "ASX", "currency": "AUD", "market_cap": 9733499, "market_cap_b": 0.01, "pe_trailing": null, "pe_forward": -0.20000002, "pb_ratio": 2.0, "ps_ratio": 0.6682464, "ev_ebitda": -1.009, "peg_ratio": null, "graham_number_check": null, "roe": -131.28, "roa": -43.94, "gross_margin": 16.77, "operating_margin": -365.33, "profit_margin": -80.55, "revenue_growth": -40.4, "earnings_growth": null, "current_ratio": 0.622, "debt_to_equity": 3.41, "quick_ratio": 0.358, "total_debt": 10479239, "total_cash": 3297134, "net_cash": -7182105, "free_cash_flow": 728407, "operating_cash_flow": -9719801, "fcf_yield": 7.48, "dividend_yield": null, "payout_ratio": 0.0, "shares_outstanding": 4866749369, "eps_positive_years": 0, "eps_total_years": 4, "earnings_cagr": null, "margin_trend": "expanding", "margin_trend_delta": 35.99, "roic": -53.87, "capex_to_net_income": null, "shares_change_pct": 99.64, "shares_trend": "increasing", "dividend_years": 0, "insider_pct": 46.02, "institution_pct": 20.7, "valid": true, "fetch_time": "2026-03-03T16:04:16.306228"}