{"ticker": "SHOP", "name": "Shopify Inc.", "sector": "Technology", "industry": "Software - Application", "exchange": "US", "currency": "USD", "market_cap": 155800879104, "market_cap_b": 155.8, "pe_trailing": 127.0, "pe_forward": 52.089375, "pb_ratio": 11.553275, "ps_ratio": 13.48225, "ev_ebitda": 77.774, "peg_ratio": null, "graham_number_check": 1467.265925, "roe": 9.84, "roa": 8.15, "gross_margin": 48.07, "operating_margin": 20.29, "profit_margin": 10.65, "revenue_growth": 30.6, "earnings_growth": -42.3, "current_ratio": 5.96, "debt_to_equity": 0.01, "quick_ratio": 4.584, "total_debt": 188000000, "total_cash": 5847000064, "net_cash": 5659000064, "free_cash_flow": 1286249984, "operating_cash_flow": 2032999936, "fcf_yield": 0.83, "dividend_yield": null, "payout_ratio": 0.0, "shares_outstanding": 1226037779, "eps_positive_years": 3, "eps_total_years": 4, "earnings_cagr": null, "margin_trend": "stable", "margin_trend_delta": -1.11, "roic": 11.66, "capex_to_net_income": 2.11, "shares_change_pct": 2.26, "shares_trend": "increasing", "dividend_years": 0, "insider_pct": 0.37, "institution_pct": 73.48, "valid": true, "fetch_time": "2026-03-03T07:42:33.369747"}