{"ticker": "SLZ.AX", "name": "Sultan Resources Limited", "sector": "Basic Materials", "industry": "Other Industrial Metals & Mining", "exchange": "ASX", "currency": "AUD", "market_cap": 8777431, "market_cap_b": 0.01, "pe_trailing": null, "pe_forward": null, "pb_ratio": 0.7894737, "ps_ratio": 323.02032, "ev_ebitda": -6.206, "peg_ratio": null, "graham_number_check": null, "roe": -78.12, "roa": -46.34, "gross_margin": 100.0, "operating_margin": 209361.91, "profit_margin": 0.0, "revenue_growth": null, "earnings_growth": null, "current_ratio": 0.332, "debt_to_equity": null, "quick_ratio": 0.265, "total_debt": 0, "total_cash": 81751, "net_cash": 81751, "free_cash_flow": 1258086, "operating_cash_flow": -502257, "fcf_yield": 14.33, "dividend_yield": null, "payout_ratio": 0.0, "shares_outstanding": 585162042, "eps_positive_years": 0, "eps_total_years": 4, "earnings_cagr": null, "roic": -7.41, "capex_to_net_income": null, "shares_change_pct": 179.42, "shares_trend": "increasing", "dividend_years": 0, "insider_pct": 30.98, "institution_pct": 0.0, "valid": true, "fetch_time": "2026-03-03T16:10:41.458377"}