{"ticker": "SSH.AX", "name": "SSH Group Limited", "sector": "Industrials", "industry": "Specialty Business Services", "exchange": "ASX", "currency": "AUD", "market_cap": 21795666, "market_cap_b": 0.02, "pe_trailing": 20.0, "pe_forward": null, "pb_ratio": 1.5625, "ps_ratio": 0.5821171, "ev_ebitda": 6.103, "peg_ratio": null, "graham_number_check": 31.25, "roe": 6.2, "roa": 4.11, "gross_margin": 34.64, "operating_margin": 8.35, "profit_margin": 1.41, "revenue_growth": -16.4, "earnings_growth": -16.9, "current_ratio": 0.615, "debt_to_equity": 2.62, "quick_ratio": 0.575, "total_debt": 24995196, "total_cash": 3954228, "net_cash": -21040968, "free_cash_flow": 4926567, "operating_cash_flow": 4430843, "fcf_yield": 22.6, "dividend_yield": null, "payout_ratio": 0.0, "shares_outstanding": 108978329, "eps_positive_years": 2, "eps_total_years": 4, "earnings_cagr": null, "margin_trend": "expanding", "margin_trend_delta": 22.3, "roic": 6.79, "capex_to_net_income": 42.38, "shares_change_pct": 19.27, "shares_trend": "increasing", "dividend_years": 0, "insider_pct": 56.95, "institution_pct": 0.0, "valid": true, "fetch_time": "2026-03-03T16:08:37.302738"}