{"ticker": "STM", "name": "STMicroelectronics N.V.", "sector": "Technology", "industry": "Semiconductors", "exchange": "US", "currency": "USD", "market_cap": 30235215872, "market_cap_b": 30.24, "pe_trailing": 185.99998, "pe_forward": 17.537886, "pb_ratio": 1.6690762, "ps_ratio": 2.5623064, "ev_ebitda": 11.738, "peg_ratio": null, "graham_number_check": 310.44813981847597, "roe": 1.0, "roa": 1.25, "gross_margin": 33.89, "operating_margin": 7.39, "profit_margin": 1.41, "revenue_growth": 0.2, "earnings_growth": null, "current_ratio": 3.363, "debt_to_equity": 0.13, "quick_ratio": 2.3, "total_debt": 2353999872, "total_cash": 4921999872, "net_cash": 2568000000, "free_cash_flow": -407375008, "operating_cash_flow": 2152000000, "fcf_yield": -1.35, "dividend_yield": 108.0, "payout_ratio": 200.0, "shares_outstanding": 888768152, "eps_positive_years": 4, "eps_total_years": 4, "earnings_cagr": -54.75, "margin_trend": "declining", "margin_trend_delta": -13.45, "roic": 1.4, "capex_to_net_income": 1327.71, "shares_change_pct": 0.0, "shares_trend": "stable", "dividend_years": 26, "insider_pct": 0.01, "institution_pct": 10.45, "valid": true, "fetch_time": "2026-03-03T07:52:44.303288"}