{"ticker": "TNL", "name": "Travel + Leisure Co.", "sector": "Consumer Cyclical", "industry": "Travel Services", "exchange": "US", "currency": "USD", "market_cap": 4561274368, "market_cap_b": 4.56, "pe_trailing": 21.25, "pe_forward": 8.6116, "pb_ratio": -4.698849, "ps_ratio": 1.1343632, "ev_ebitda": 10.821, "peg_ratio": null, "graham_number_check": null, "roe": null, "roa": 7.44, "gross_margin": 49.99, "operating_margin": 21.95, "profit_margin": 5.72, "revenue_growth": 5.6, "earnings_growth": null, "current_ratio": 3.08, "debt_to_equity": null, "quick_ratio": 2.08, "total_debt": 5759000064, "total_cash": 288000000, "net_cash": -5471000064, "free_cash_flow": 512875008, "operating_cash_flow": 640000000, "fcf_yield": 11.24, "dividend_yield": 306.0, "payout_ratio": 65.12, "shares_outstanding": 62397734, "eps_positive_years": 4, "eps_total_years": 4, "earnings_cagr": -10.41, "margin_trend": "declining", "margin_trend_delta": -3.53, "roic": 9.7, "capex_to_net_income": 50.87, "shares_change_pct": 1.36, "shares_trend": "stable", "dividend_years": 18, "insider_pct": 5.21, "institution_pct": 100.95, "valid": true, "fetch_time": "2026-03-03T08:17:56.996232"}