{"ticker": "XGL.AX", "name": "Xamble Group Limited", "sector": "Communication Services", "industry": "Advertising Agencies", "exchange": "ASX", "currency": "AUD", "market_cap": 5876247, "market_cap_b": 0.01, "pe_trailing": null, "pe_forward": null, "pb_ratio": -13.0, "ps_ratio": 0.8683115, "ev_ebitda": -1.91, "peg_ratio": null, "graham_number_check": null, "roe": -139.76, "roa": -42.49, "gross_margin": 38.89, "operating_margin": -42.84, "profit_margin": -35.81, "revenue_growth": -9.4, "earnings_growth": null, "current_ratio": 0.866, "debt_to_equity": 0.91, "quick_ratio": 0.765, "total_debt": 196911, "total_cash": 968187, "net_cash": 771276, "free_cash_flow": -519573, "operating_cash_flow": -2660247, "fcf_yield": -8.84, "dividend_yield": null, "payout_ratio": 0.0, "shares_outstanding": 452018963, "eps_positive_years": 0, "eps_total_years": 4, "earnings_cagr": null, "margin_trend": "stable", "margin_trend_delta": -1.66, "roic": null, "capex_to_net_income": null, "shares_change_pct": 19.79, "shares_trend": "increasing", "dividend_years": 0, "insider_pct": 76.43, "institution_pct": 0.0, "valid": true, "fetch_time": "2026-03-03T16:25:18.970705"}